[{"ID":"Recipe_WaterCollector_1","Sort":1,"Category":1,"Name":{"Chinese":"少量水","English":"少量水"},"Raw":[],"Product":{"id":"Item_Wood_11","num":3},"TimeCost":6,"ExpRecipe":10},{"ID":"Recipe_WaterPurifier_1","Sort":1,"Category":2,"Name":{"Chinese":"大量水","English":"大量水"},"Raw":[],"Product":{"id":"Item_Wood_11","num":15},"TimeCost":6,"ExpRecipe":10},{"ID":"Recipe_SeedBox_1","Sort":1,"Category":3,"Name":{"Chinese":"种籽","English":"种籽"},"Raw":[],"Product":{"id":"Item_Wood_3","num":5},"TimeCost":6,"ExpRecipe":10},{"ID":"Recipe_SeedPlot_1","Sort":1,"Category":5,"Name":{"Chinese":"苍枝","English":"苍枝"},"Raw":[{"id":"Item_Wood_3","num":1},{"id":"Item_Wood_11","num":1}],"Product":{"id":"Item_Wood_1","num":1},"TimeCost":12,"ExpRecipe":20},{"ID":"Recipe_SeedPlot_2","Sort":2,"Category":5,"Name":{"Chinese":"原木","English":"原木"},"Raw":[{"id":"Item_Wood_3","num":1},{"id":"Item_Wood_11","num":1}],"Product":{"id":"Item_Wood_2","num":1},"TimeCost":12,"ExpRecipe":20},{"ID":"Recipe_SeedPlot_3","Sort":3,"Category":5,"Name":{"Chinese":"甜薯","English":"甜薯"},"Raw":[{"id":"Item_Wood_3","num":1},{"id":"Item_Wood_11","num":1}],"Product":{"id":"Item_Vegetable_1","num":1},"TimeCost":12,"ExpRecipe":20},{"ID":"Recipe_Refine_7","Sort":7,"Category":7,"Name":{"Chinese":"错金拓片","English":"错金拓片"},"Raw":[{"id":"Item_Stone_12","num":1},{"id":"Item_Wood_11","num":1}],"Product":{"id":"Item_Metal_10","num":1},"TimeCost":18,"ExpRecipe":30},{"ID":"Recipe_SeedPlot_4","Sort":4,"Category":5,"Name":{"Chinese":"生菜","English":"生菜"},"Raw":[{"id":"Item_Wood_3","num":1},{"id":"Item_Wood_11","num":1}],"Product":{"id":"Item_Vegetable_2","num":1},"TimeCost":12,"ExpRecipe":20},{"ID":"Recipe_Refine_8","Sort":8,"Category":7,"Name":{"Chinese":"钢","English":"钢"},"Raw":[{"id":"Item_Metal_8","num":1},{"id":"Item_Wood_11","num":1},{"id":"Item_Wood_4","num":1}],"Product":{"id":"Item_Metal_11","num":1},"TimeCost":24,"ExpRecipe":40},{"ID":"Recipe_SeedPlot_5","Sort":5,"Category":5,"Name":{"Chinese":"亚麻","English":"亚麻"},"Raw":[{"id":"Item_Wood_3","num":1},{"id":"Item_Wood_11","num":1}],"Product":{"id":"Item_Fabric_1","num":1},"TimeCost":12,"ExpRecipe":20},{"ID":"Recipe_SeedPlot_6","Sort":6,"Category":5,"Name":{"Chinese":"白芍","English":"白芍"},"Raw":[{"id":"Item_Wood_3","num":1},{"id":"Item_Wood_11","num":1}],"Product":{"id":"Item_Medicine_31","num":1},"TimeCost":12,"ExpRecipe":20},{"ID":"Recipe_Refine_9","Sort":9,"Category":7,"Name":{"Chinese":"密钨卷","English":"密钨卷"},"Raw":[{"id":"Item_Stone_13","num":1},{"id":"Item_Wood_11","num":1}],"Product":{"id":"Item_Metal_12","num":1},"TimeCost":24,"ExpRecipe":40},{"ID":"Recipe_Kitchen_1","Sort":1,"Category":13,"Name":{"Chinese":"薯薯生活沙拉","English":"薯薯生活沙拉"},"Raw":[{"id":"Item_Vegetable_1","num":1},{"id":"Item_Vegetable_2","num":1}],"Product":{"id":"Item_Feed_1","num":1},"TimeCost":18,"ExpRecipe":30},{"ID":"Recipe_SeedPlot_8","Sort":8,"Category":5,"Name":{"Chinese":"稻米","English":"稻米"},"Raw":[{"id":"Item_Wood_3","num":1},{"id":"Item_Wood_11","num":1}],"Product":{"id":"Item_Vegetable_3","num":1},"TimeCost":18,"ExpRecipe":30},{"ID":"Recipe_Refine_10","Sort":10,"Category":7,"Name":{"Chinese":"轻钛条","English":"轻钛条"},"Raw":[{"id":"Item_Stone_14","num":1},{"id":"Item_Wood_11","num":1}],"Product":{"id":"Item_Metal_13","num":1},"TimeCost":24,"ExpRecipe":40},{"ID":"Recipe_SeedPlot_7","Sort":7,"Category":5,"Name":{"Chinese":"曼珠葛","English":"曼珠葛"},"Raw":[{"id":"Item_Wood_3","num":1},{"id":"Item_Wood_11","num":1}],"Product":{"id":"Item_Medicine_32","num":1},"TimeCost":18,"ExpRecipe":30},{"ID":"Recipe_SeedPlot_9","Sort":9,"Category":5,"Name":{"Chinese":"荆藤异果","English":"荆藤异果"},"Raw":[{"id":"Item_Wood_3","num":1},{"id":"Item_Wood_11","num":1}],"Product":{"id":"Item_Juice_6","num":1},"TimeCost":18,"ExpRecipe":30},{"ID":"Recipe_Handwork_1","Sort":1,"Category":8,"Name":{"Chinese":"木板","English":"木板"},"Raw":[{"id":"Item_Wood_2","num":1}],"Product":{"id":"Item_Wood_5","num":1},"TimeCost":24,"ExpRecipe":40},{"ID":"Recipe_Kitchen_2","Sort":2,"Category":13,"Name":{"Chinese":"昨夜甜粥","English":"昨夜甜粥"},"Raw":[{"id":"Item_Vegetable_1","num":1},{"id":"Item_Vegetable_3","num":1},{"id":"Item_Wood_11","num":1}],"Product":{"id":"Item_Feed_2","num":1},"TimeCost":24,"ExpRecipe":40},{"ID":"Recipe_Refine_1","Sort":1,"Category":7,"Name":{"Chinese":"石板","English":"石板"},"Raw":[{"id":"Item_Stone_2","num":1}],"Product":{"id":"Item_Stone_4","num":1},"TimeCost":12,"ExpRecipe":20},{"ID":"Recipe_Handwork_2","Sort":2,"Category":8,"Name":{"Chinese":"麻布","English":"麻布"},"Raw":[{"id":"Item_Fabric_1","num":1}],"Product":{"id":"Item_Fabric_2","num":1},"TimeCost":24,"ExpRecipe":40},{"ID":"Recipe_Pharmacy_2","Sort":2,"Category":9,"Name":{"Chinese":"曼珠葛制剂","English":"曼珠葛制剂"},"Raw":[{"id":"Item_Medicine_32","num":1}],"Product":{"id":"Item_Medicine_34","num":1},"TimeCost":24,"ExpRecipe":40},{"ID":"Recipe_Kitchen_3","Sort":3,"Category":13,"Name":{"Chinese":"醉晕晕蛋羹","English":"醉晕晕蛋羹"},"Raw":[{"id":"Item_Wood_14","num":1},{"id":"Item_Meat_2","num":1}],"Product":{"id":"Item_Feed_3","num":1},"TimeCost":30,"ExpRecipe":50},{"ID":"Recipe_Kitchen_10","Sort":10,"Category":13,"Name":{"Chinese":"闪电小饼干","English":"闪电小饼干"},"Raw":[{"id":"Item_Vegetable_5","num":1},{"id":"Item_Vegetable_3","num":1},{"id":"Item_Meat_2","num":1},{"id":"Item_Meat_3","num":1}],"Product":{"id":"Item_Snack_5","num":1},"TimeCost":24,"ExpRecipe":40},{"ID":"Recipe_Handwork_3","Sort":3,"Category":8,"Name":{"Chinese":"螺旋笛","English":"螺旋笛"},"Raw":[{"id":"Item_Stone_8","num":1},{"id":"Item_Wood_5","num":1}],"Product":{"id":"Item_Magic_2","num":1},"TimeCost":24,"ExpRecipe":40},{"ID":"Recipe_Refine_2","Sort":2,"Category":7,"Name":{"Chinese":"玻璃","English":"玻璃"},"Raw":[{"id":"Item_Stone_3","num":1}],"Product":{"id":"Item_Stone_5","num":1},"TimeCost":12,"ExpRecipe":20},{"ID":"Recipe_Handwork_4","Sort":4,"Category":8,"Name":{"Chinese":"浮生绸","English":"浮生绸"},"Raw":[{"id":"Item_Fabric_6","num":1}],"Product":{"id":"Item_Fabric_3","num":1},"TimeCost":24,"ExpRecipe":40},{"ID":"Recipe_Kitchen_4","Sort":4,"Category":13,"Name":{"Chinese":"奇妙冒险大饭卷","English":"奇妙冒险大饭卷"},"Raw":[{"id":"Item_Vegetable_3","num":1},{"id":"Item_Meat_1","num":1},{"id":"Item_Meat_2","num":1}],"Product":{"id":"Item_Feed_4","num":1},"TimeCost":24,"ExpRecipe":40},{"ID":"Recipe_Pharmacy_3","Sort":3,"Category":9,"Name":{"Chinese":"神经橘苷片","English":"神经橘苷片"},"Raw":[{"id":"Item_Medicine_33","num":1},{"id":"Item_Vegetable_22","num":1}],"Product":{"id":"Item_Medicine_1","num":1},"TimeCost":24,"ExpRecipe":40},{"ID":"Recipe_Pharmacy_5","Sort":5,"Category":9,"Name":{"Chinese":"褪红素","English":"褪红素"},"Raw":[{"id":"Item_Medicine_34","num":1},{"id":"Item_Medicine_22","num":1},{"id":"Item_Wood_13","num":1}],"Product":{"id":"Item_Medicine_21","num":1},"TimeCost":24,"ExpRecipe":40},{"ID":"Recipe_Kitchen_5","Sort":5,"Category":13,"Name":{"Chinese":"今晚去吃吧烤肉","English":"今晚去吃吧烤肉"},"Raw":[{"id":"Item_Vegetable_2","num":1},{"id":"Item_Meat_1","num":1},{"id":"Item_Medicine_23","num":1}],"Product":{"id":"Item_Feed_5","num":1},"TimeCost":24,"ExpRecipe":40},{"ID":"Recipe_Refine_3","Sort":3,"Category":7,"Name":{"Chinese":"铜锭","English":"铜锭"},"Raw":[{"id":"Item_Stone_9","num":1},{"id":"Item_Wood_11","num":1}],"Product":{"id":"Item_Metal_7","num":1},"TimeCost":12,"ExpRecipe":20},{"ID":"Recipe_Kitchen_11","Sort":11,"Category":13,"Name":{"Chinese":"蓬蓬小饼干","English":"蓬蓬小饼干"},"Raw":[{"id":"Item_Vegetable_5","num":1},{"id":"Item_Vegetable_3","num":1},{"id":"Item_Meat_2","num":1},{"id":"Item_Meat_3","num":1}],"Product":{"id":"Item_Snack_6","num":1},"TimeCost":24,"ExpRecipe":40},{"ID":"Recipe_Pharmacy_1","Sort":1,"Category":9,"Name":{"Chinese":"白芍粉","English":"白芍粉"},"Raw":[{"id":"Item_Medicine_31","num":1}],"Product":{"id":"Item_Medicine_33","num":1},"TimeCost":24,"ExpRecipe":40},{"ID":"Recipe_Pharmacy_4","Sort":4,"Category":9,"Name":{"Chinese":"活性酶","English":"活性酶"},"Raw":[{"id":"Item_Medicine_34","num":1},{"id":"Item_Medicine_33","num":1}],"Product":{"id":"Item_Medicine_22","num":1},"TimeCost":24,"ExpRecipe":40},{"ID":"Recipe_Kitchen_6","Sort":6,"Category":13,"Name":{"Chinese":"刀叉小饼干","English":"刀叉小饼干"},"Raw":[{"id":"Item_Vegetable_1","num":1},{"id":"Item_Vegetable_3","num":1},{"id":"Item_Meat_2","num":1},{"id":"Item_Meat_3","num":1}],"Product":{"id":"Item_Snack_1","num":1},"TimeCost":24,"ExpRecipe":40},{"ID":"Recipe_Refine_4","Sort":4,"Category":7,"Name":{"Chinese":"铁锭","English":"铁锭"},"Raw":[{"id":"Item_Stone_10","num":1},{"id":"Item_Wood_11","num":1}],"Product":{"id":"Item_Metal_8","num":1},"TimeCost":12,"ExpRecipe":20},{"ID":"Recipe_Pharmacy_6","Sort":6,"Category":9,"Name":{"Chinese":"阿法林酊","English":"阿法林酊"},"Raw":[{"id":"Item_Medicine_34","num":1},{"id":"Item_Medicine_22","num":1},{"id":"Item_Wood_14","num":1}],"Product":{"id":"Item_Medicine_24","num":1},"TimeCost":24,"ExpRecipe":40},{"ID":"Recipe_Liquor_1","Sort":1,"Category":10,"Name":{"Chinese":"糖浆","English":"糖浆"},"Raw":[{"id":"Item_Vegetable_1","num":1}],"Product":{"id":"Item_Vegetable_5","num":1},"TimeCost":24,"ExpRecipe":40},{"ID":"Recipe_Kitchen_7","Sort":7,"Category":13,"Name":{"Chinese":"纸箱小饼干","English":"纸箱小饼干"},"Raw":[{"id":"Item_Vegetable_1","num":1},{"id":"Item_Vegetable_3","num":1},{"id":"Item_Meat_2","num":1},{"id":"Item_Meat_3","num":1}],"Product":{"id":"Item_Snack_2","num":1},"TimeCost":24,"ExpRecipe":40},{"ID":"Recipe_Kitchen_8","Sort":8,"Category":13,"Name":{"Chinese":"鱼尾小饼干","English":"鱼尾小饼干"},"Raw":[{"id":"Item_Vegetable_1","num":1},{"id":"Item_Vegetable_3","num":1},{"id":"Item_Meat_2","num":1},{"id":"Item_Meat_3","num":1}],"Product":{"id":"Item_Snack_3","num":1},"TimeCost":24,"ExpRecipe":40},{"ID":"Recipe_Liquor_2","Sort":2,"Category":10,"Name":{"Chinese":"叶青素","English":"叶青素"},"Raw":[{"id":"Item_Vegetable_2","num":1}],"Product":{"id":"Item_Wood_12","num":1},"TimeCost":24,"ExpRecipe":40},{"ID":"Recipe_Refine_5","Sort":5,"Category":7,"Name":{"Chinese":"焦碳","English":"焦碳"},"Raw":[{"id":"Item_Wood_2","num":1}],"Product":{"id":"Item_Wood_4","num":1},"TimeCost":18,"ExpRecipe":30},{"ID":"Recipe_Pharmacy_7","Sort":7,"Category":9,"Name":{"Chinese":"可可脉因","English":"可可脉因"},"Raw":[{"id":"Item_Medicine_33","num":1},{"id":"Item_Medicine_22","num":1},{"id":"Item_Wood_12","num":1}],"Product":{"id":"Item_Medicine_23","num":1},"TimeCost":24,"ExpRecipe":40},{"ID":"Recipe_Liquor_6","Sort":6,"Category":10,"Name":{"Chinese":"忘却果汁","English":"忘却果汁"},"Raw":[{"id":"Item_Juice_6","num":1},{"id":"Item_Wood_14","num":1},{"id":"Item_Meat_3","num":1}],"Product":{"id":"Item_Juice_2","num":1},"TimeCost":24,"ExpRecipe":40},{"ID":"Recipe_Liquor_9","Sort":9,"Category":10,"Name":{"Chinese":"敲晕果汁！","English":"敲晕果汁！"},"Raw":[{"id":"Item_Juice_1","num":1},{"id":"Item_Wood_16","num":1},{"id":"Item_Medicine_24","num":1}],"Product":{"id":"Item_Juice_5","num":1},"TimeCost":24,"ExpRecipe":40},{"ID":"Recipe_Liquor_3","Sort":3,"Category":10,"Name":{"Chinese":"甘油酯","English":"甘油酯"},"Raw":[{"id":"Item_Fabric_1","num":1}],"Product":{"id":"Item_Wood_13","num":1},"TimeCost":24,"ExpRecipe":40},{"ID":"Recipe_Refine_6","Sort":6,"Category":7,"Name":{"Chinese":"秘银拓片","English":"秘银拓片"},"Raw":[{"id":"Item_Stone_11","num":1},{"id":"Item_Wood_11","num":1}],"Product":{"id":"Item_Metal_9","num":1},"TimeCost":18,"ExpRecipe":30},{"ID":"Recipe_Calculus_1","Sort":1,"Category":16,"Name":{"Chinese":"测析数据模块I","English":"测析数据模块I"},"Raw":[{"id":"Item_Stone_4","num":1},{"id":"Item_Wood_5","num":1}],"Product":{"id":"Item_Calculus_1","num":1},"TimeCost":18,"ExpRecipe":30},{"ID":"Recipe_Kitchen_9","Sort":9,"Category":13,"Name":{"Chinese":"猫爪小饼干","English":"猫爪小饼干"},"Raw":[{"id":"Item_Vegetable_1","num":1},{"id":"Item_Vegetable_3","num":1},{"id":"Item_Meat_2","num":1},{"id":"Item_Meat_3","num":1}],"Product":{"id":"Item_Snack_4","num":1},"TimeCost":24,"ExpRecipe":40},{"ID":"Recipe_Pharmacy_8","Sort":8,"Category":9,"Name":{"Chinese":"荷兴奋剂","English":"荷兴奋剂"},"Raw":[{"id":"Item_Magic_33","num":1},{"id":"Item_Medicine_21","num":1},{"id":"Item_Medicine_24","num":1}],"Product":{"id":"Item_Medicine_11","num":1},"TimeCost":24,"ExpRecipe":40},{"ID":"Recipe_Liquor_7","Sort":7,"Category":10,"Name":{"Chinese":"甜蜜果汁","English":"甜蜜果汁"},"Raw":[{"id":"Item_Juice_6","num":1},{"id":"Item_Medicine_23","num":1},{"id":"Item_Meat_3","num":1}],"Product":{"id":"Item_Juice_3","num":1},"TimeCost":24,"ExpRecipe":40},{"ID":"Recipe_Calculus_2","Sort":2,"Category":16,"Name":{"Chinese":"术法公式总结I","English":"术法公式总结I"},"Raw":[{"id":"Item_Stone_8","num":1}],"Product":{"id":"Item_Calculus_2","num":1},"TimeCost":18,"ExpRecipe":30},{"ID":"Recipe_Liquor_4","Sort":4,"Category":10,"Name":{"Chinese":"酒露醇","English":"酒露醇"},"Raw":[{"id":"Item_Vegetable_3","num":1}],"Product":{"id":"Item_Wood_14","num":1},"TimeCost":24,"ExpRecipe":40},{"ID":"Recipe_Calculus_9","Sort":9,"Category":16,"Name":{"Chinese":"测析数据模块V","English":"测析数据模块V"},"Raw":[{"id":"Item_Metal_19","num":1}],"Product":{"id":"Item_Calculus_9","num":1},"TimeCost":42,"ExpRecipe":70},{"ID":"Recipe_Processor_1","Sort":1,"Category":12,"Name":{"Chinese":"简单回路","English":"简单回路"},"Raw":[{"id":"Item_Metal_8","num":1}],"Product":{"id":"Item_Metal_14","num":1},"TimeCost":30,"ExpRecipe":50},{"ID":"Recipe_Pharmacy_9","Sort":9,"Category":9,"Name":{"Chinese":"参麻粹剂","English":"参麻粹剂"},"Raw":[{"id":"Item_Magic_33","num":1},{"id":"Item_Medicine_24","num":1},{"id":"Item_Medicine_23","num":1}],"Product":{"id":"Item_Medicine_12","num":1},"TimeCost":24,"ExpRecipe":40},{"ID":"Recipe_Processor_9","Sort":9,"Category":12,"Name":{"Chinese":"光折伞帆","English":"光折伞帆"},"Raw":[{"id":"Item_Metal_20","num":1},{"id":"Item_Metal_21","num":1},{"id":"Item_Fabric_5","num":1},{"id":"Item_Magic_5","num":1}],"Product":{"id":"Item_Metal_22","num":1},"TimeCost":48,"ExpRecipe":80},{"ID":"Recipe_Calculus_3","Sort":3,"Category":16,"Name":{"Chinese":"测析数据模块II","English":"测析数据模块II"},"Raw":[{"id":"Item_Metal_7","num":1}],"Product":{"id":"Item_Calculus_3","num":1},"TimeCost":24,"ExpRecipe":40},{"ID":"Recipe_Calculus_10","Sort":10,"Category":16,"Name":{"Chinese":"术法公式总结V","English":"术法公式总结V"},"Raw":[{"id":"Item_Magic_4","num":2}],"Product":{"id":"Item_Calculus_10","num":1},"TimeCost":42,"ExpRecipe":70},{"ID":"Recipe_Liquor_5","Sort":5,"Category":10,"Name":{"Chinese":"不喵红茶","English":"不喵红茶"},"Raw":[{"id":"Item_Juice_6","num":1},{"id":"Item_Wood_14","num":1},{"id":"Item_Vegetable_5","num":1}],"Product":{"id":"Item_Juice_1","num":1},"TimeCost":24,"ExpRecipe":40},{"ID":"Recipe_Calculus_4","Sort":4,"Category":16,"Name":{"Chinese":"术法公式总结II","English":"术法公式总结II"},"Raw":[{"id":"Item_Magic_3","num":1}],"Product":{"id":"Item_Calculus_4","num":1},"TimeCost":24,"ExpRecipe":40},{"ID":"Recipe_Processor_2","Sort":2,"Category":12,"Name":{"Chinese":"电导基元","English":"电导基元"},"Raw":[{"id":"Item_Metal_7","num":1}],"Product":{"id":"Item_Metal_15","num":1},"TimeCost":36,"ExpRecipe":60},{"ID":"Recipe_Pharmacy_10","Sort":10,"Category":9,"Name":{"Chinese":"绯钠注剂","English":"绯钠注剂"},"Raw":[{"id":"Item_Magic_33","num":1},{"id":"Item_Medicine_21","num":1},{"id":"Item_Medicine_23","num":1}],"Product":{"id":"Item_Medicine_13","num":1},"TimeCost":24,"ExpRecipe":40},{"ID":"Recipe_Processor_10","Sort":10,"Category":12,"Name":{"Chinese":"织星镜","English":"织星镜"},"Raw":[{"id":"Item_Metal_20","num":1},{"id":"Item_Metal_21","num":1},{"id":"Item_Stone_7","num":1},{"id":"Item_Magic_6","num":1}],"Product":{"id":"Item_Metal_23","num":1},"TimeCost":48,"ExpRecipe":80},{"ID":"Recipe_Calculus_5","Sort":5,"Category":16,"Name":{"Chinese":"测析数据模块III","English":"测析数据模块III"},"Raw":[{"id":"Item_Metal_11","num":1}],"Product":{"id":"Item_Calculus_5","num":1},"TimeCost":30,"ExpRecipe":50},{"ID":"Recipe_Calculus_11","Sort":11,"Category":16,"Name":{"Chinese":"测析数据模块VI","English":"测析数据模块VI"},"Raw":[{"id":"Item_Metal_20","num":1}],"Product":{"id":"Item_Calculus_11","num":1},"TimeCost":48,"ExpRecipe":80},{"ID":"Recipe_DiveStation_2","Sort":2,"Category":6,"Name":{"Chinese":"杂色硅砂","English":"杂色硅砂"},"Raw":[],"Product":{"id":"Item_Stone_3","num":1},"TimeCost":10,"ExpRecipe":5},{"ID":"Recipe_Processor_3","Sort":3,"Category":12,"Name":{"Chinese":"集成回路","English":"集成回路"},"Raw":[{"id":"Item_Metal_14","num":1},{"id":"Item_Metal_9","num":1}],"Product":{"id":"Item_Metal_16","num":1},"TimeCost":36,"ExpRecipe":60},{"ID":"Recipe_Calculus_6","Sort":6,"Category":16,"Name":{"Chinese":"术法公式总结III","English":"术法公式总结III"},"Raw":[{"id":"Item_Magic_3","num":2}],"Product":{"id":"Item_Calculus_6","num":1},"TimeCost":30,"ExpRecipe":50},{"ID":"Recipe_Aggregator_1","Sort":1,"Category":11,"Name":{"Chinese":"金刚晶","English":"金刚晶"},"Raw":[{"id":"Item_Wood_4","num":1}],"Product":{"id":"Item_Wood_8","num":1},"TimeCost":30,"ExpRecipe":50},{"ID":"Recipe_CreaturePro_1","Sort":1,"Category":14,"Name":{"Chinese":"浮生丝","English":"浮生丝"},"Raw":[{"id":"Item_Wood_11","num":1}],"Product":{"id":"Item_Fabric_6","num":1},"TimeCost":10,"ExpRecipe":0},{"ID":"Recipe_DiveStation_3","Sort":3,"Category":6,"Name":{"Chinese":"重晶流莹","English":"重晶流莹"},"Raw":[],"Product":{"id":"Item_Stone_8","num":1},"TimeCost":15,"ExpRecipe":5},{"ID":"Recipe_Calculus_12","Sort":12,"Category":16,"Name":{"Chinese":"术法公式总结VI","English":"术法公式总结VI"},"Raw":[{"id":"Item_Magic_5","num":1},{"id":"Item_Magic_6","num":1}],"Product":{"id":"Item_Calculus_12","num":1},"TimeCost":48,"ExpRecipe":80},{"ID":"Recipe_Calculus_7","Sort":7,"Category":16,"Name":{"Chinese":"测析数据模块IV","English":"测析数据模块IV"},"Raw":[{"id":"Item_Metal_16","num":1}],"Product":{"id":"Item_Calculus_7","num":1},"TimeCost":36,"ExpRecipe":60},{"ID":"Recipe_Processor_4","Sort":4,"Category":12,"Name":{"Chinese":"阶导凝晶","English":"阶导凝晶"},"Raw":[{"id":"Item_Metal_15","num":1},{"id":"Item_Wood_8","num":1}],"Product":{"id":"Item_Metal_17","num":1},"TimeCost":42,"ExpRecipe":70},{"ID":"Recipe_Aggregator_2","Sort":2,"Category":11,"Name":{"Chinese":"石墨网","English":"石墨网"},"Raw":[{"id":"Item_Wood_4","num":1}],"Product":{"id":"Item_Wood_7","num":1},"TimeCost":30,"ExpRecipe":50},{"ID":"Recipe_CreaturePro_2","Sort":2,"Category":14,"Name":{"Chinese":"蛋蛋","English":"蛋蛋"},"Raw":[{"id":"Item_Wood_11","num":1}],"Product":{"id":"Item_Meat_2","num":1},"TimeCost":10,"ExpRecipe":0},{"ID":"Recipe_DiveStation_4","Sort":4,"Category":6,"Name":{"Chinese":"次生灼铜","English":"次生灼铜"},"Raw":[],"Product":{"id":"Item_Stone_9","num":1},"TimeCost":15,"ExpRecipe":5},{"ID":"Recipe_Integrator_1","Sort":1,"Category":4,"Name":{"Chinese":"光流基粒","English":"光流基粒"},"Raw":[{"id":"Item_Stone_8","num":2}],"Product":{"id":"Item_Magic_3","num":1},"TimeCost":30,"ExpRecipe":50},{"ID":"Recipe_Pharmacy_11","Sort":11,"Category":9,"Name":{"Chinese":"繁育药剂","English":"繁育药剂"},"Raw":[{"id":"Item_Wood_11","num":1}],"Product":{"id":"Item_Medicine_30","num":1},"TimeCost":30,"ExpRecipe":15},{"ID":"Recipe_Processor_5","Sort":5,"Category":12,"Name":{"Chinese":"核芯回路","English":"核芯回路"},"Raw":[{"id":"Item_Metal_16","num":1},{"id":"Item_Metal_12","num":1}],"Product":{"id":"Item_Metal_18","num":1},"TimeCost":42,"ExpRecipe":70},{"ID":"Recipe_CreaturePro_3","Sort":3,"Category":14,"Name":{"Chinese":"鲜牛乳","English":"鲜牛乳"},"Raw":[{"id":"Item_Wood_11","num":1}],"Product":{"id":"Item_Meat_3","num":1},"TimeCost":10,"ExpRecipe":0},{"ID":"Recipe_Aggregator_3","Sort":3,"Category":11,"Name":{"Chinese":"聚脂纤维","English":"聚脂纤维"},"Raw":[{"id":"Item_Wood_13","num":1},{"id":"Item_Wood_5","num":1}],"Product":{"id":"Item_Wood_15","num":1},"TimeCost":30,"ExpRecipe":50},{"ID":"Recipe_DiveStation_5","Sort":5,"Category":6,"Name":{"Chinese":"磷铁结核","English":"磷铁结核"},"Raw":[],"Product":{"id":"Item_Stone_10","num":1},"TimeCost":15,"ExpRecipe":5},{"ID":"Recipe_Integrator_2","Sort":2,"Category":4,"Name":{"Chinese":"光流集律","English":"光流集律"},"Raw":[{"id":"Item_Magic_3","num":2},{"id":"Item_Metal_10","num":1}],"Product":{"id":"Item_Magic_4","num":1},"TimeCost":36,"ExpRecipe":60},{"ID":"Recipe_Processor_6","Sort":6,"Category":12,"Name":{"Chinese":"半导阵列","English":"半导阵列"},"Raw":[{"id":"Item_Metal_17","num":1},{"id":"Item_Metal_12","num":1}],"Product":{"id":"Item_Metal_19","num":1},"TimeCost":42,"ExpRecipe":70},{"ID":"Recipe_CreaturePro_4","Sort":4,"Category":14,"Name":{"Chinese":"黏黏冻","English":"黏黏冻"},"Raw":[{"id":"Item_Wood_11","num":1}],"Product":{"id":"Item_Wood_16","num":1},"TimeCost":15,"ExpRecipe":0},{"ID":"Recipe_Aggregator_4","Sort":4,"Category":11,"Name":{"Chinese":"复合纤维束","English":"复合纤维束"},"Raw":[{"id":"Item_Wood_15","num":1},{"id":"Item_Wood_7","num":1}],"Product":{"id":"Item_Wood_9","num":1},"TimeCost":30,"ExpRecipe":50},{"ID":"Recipe_DiveStation_6","Sort":6,"Category":6,"Name":{"Chinese":"水色银","English":"水色银"},"Raw":[],"Product":{"id":"Item_Stone_11","num":1},"TimeCost":20,"ExpRecipe":10},{"ID":"Recipe_Integrator_3","Sort":3,"Category":4,"Name":{"Chinese":"日环光谱","English":"日环光谱"},"Raw":[{"id":"Item_Magic_4","num":2},{"id":"Item_Magic_7","num":1}],"Product":{"id":"Item_Magic_5","num":1},"TimeCost":42,"ExpRecipe":70},{"ID":"Recipe_Processor_7","Sort":7,"Category":12,"Name":{"Chinese":"核芯处理器","English":"核芯处理器"},"Raw":[{"id":"Item_Metal_18","num":1},{"id":"Item_Metal_19","num":1}],"Product":{"id":"Item_Metal_20","num":1},"TimeCost":42,"ExpRecipe":70},{"ID":"Recipe_DiveStation_7","Sort":7,"Category":6,"Name":{"Chinese":"闪白金","English":"闪白金"},"Raw":[],"Product":{"id":"Item_Stone_12","num":1},"TimeCost":20,"ExpRecipe":10},{"ID":"Recipe_CreaturePro_5","Sort":5,"Category":14,"Name":{"Chinese":"二向冰锥","English":"二向冰锥"},"Raw":[{"id":"Item_Wood_11","num":1}],"Product":{"id":"Item_Magic_7","num":1},"TimeCost":30,"ExpRecipe":0},{"ID":"Recipe_Aggregator_5","Sort":5,"Category":11,"Name":{"Chinese":"拟像镜面","English":"拟像镜面"},"Raw":[{"id":"Item_Stone_6","num":1},{"id":"Item_Wood_16","num":1}],"Product":{"id":"Item_Stone_7","num":1},"TimeCost":30,"ExpRecipe":50},{"ID":"Recipe_Integrator_4","Sort":4,"Category":4,"Name":{"Chinese":"月环光谱","English":"月环光谱"},"Raw":[{"id":"Item_Magic_4","num":2},{"id":"Item_Magic_8","num":1}],"Product":{"id":"Item_Magic_6","num":1},"TimeCost":42,"ExpRecipe":70},{"ID":"Recipe_Liquor_8","Sort":8,"Category":10,"Name":{"Chinese":"苦涩果汁","English":"苦涩果汁"},"Raw":[{"id":"Item_Juice_6","num":1},{"id":"Item_Medicine_21","num":1},{"id":"Item_Meat_3","num":1}],"Product":{"id":"Item_Juice_4","num":1},"TimeCost":24,"ExpRecipe":40},{"ID":"Recipe_CreatureBreed_1","Sort":1,"Category":15,"Name":{"Chinese":"龙雀","English":"龙雀"},"Raw":[{"id":"Item_Medicine_30","num":1}],"Product":{"id":"Item_Creature_1","num":1},"TimeCost":60,"ExpRecipe":0},{"ID":"Recipe_Aggregator_6","Sort":6,"Category":11,"Name":{"Chinese":"特种玻璃","English":"特种玻璃"},"Raw":[{"id":"Item_Stone_5","num":1},{"id":"Item_Wood_8","num":1}],"Product":{"id":"Item_Stone_6","num":1},"TimeCost":30,"ExpRecipe":50},{"ID":"Recipe_DiveStation_8","Sort":8,"Category":6,"Name":{"Chinese":"密层重钨","English":"密层重钨"},"Raw":[],"Product":{"id":"Item_Stone_13","num":1},"TimeCost":30,"ExpRecipe":15},{"ID":"Recipe_Processor_8","Sort":8,"Category":12,"Name":{"Chinese":"轻量框架","English":"轻量框架"},"Raw":[{"id":"Item_Metal_11","num":1},{"id":"Item_Metal_13","num":1}],"Product":{"id":"Item_Metal_21","num":1},"TimeCost":48,"ExpRecipe":80},{"ID":"Recipe_CreatureBreed_2","Sort":2,"Category":15,"Name":{"Chinese":"真谛牛","English":"真谛牛"},"Raw":[{"id":"Item_Medicine_30","num":1}],"Product":{"id":"Item_Creature_2","num":1},"TimeCost":80,"ExpRecipe":0},{"ID":"Recipe_Aggregator_7","Sort":7,"Category":11,"Name":{"Chinese":"镭射无纺布","English":"镭射无纺布"},"Raw":[{"id":"Item_Wood_9","num":1},{"id":"Item_Wood_10","num":1}],"Product":{"id":"Item_Fabric_5","num":1},"TimeCost":36,"ExpRecipe":60},{"ID":"Recipe_DiveStation_9","Sort":9,"Category":6,"Name":{"Chinese":"姴痂钛方","English":"姴痂钛方"},"Raw":[],"Product":{"id":"Item_Stone_14","num":1},"TimeCost":30,"ExpRecipe":15},{"ID":"Recipe_DiveStation_1","Sort":1,"Category":6,"Name":{"Chinese":"混碎岩","English":"混碎岩"},"Raw":[],"Product":{"id":"Item_Stone_2","num":1},"TimeCost":10,"ExpRecipe":5},{"ID":"Recipe_CreatureBreed_3","Sort":3,"Category":15,"Name":{"Chinese":"猫浮","English":"猫浮"},"Raw":[{"id":"Item_Medicine_30","num":1}],"Product":{"id":"Item_Creature_3","num":1},"TimeCost":90,"ExpRecipe":0},{"ID":"Recipe_CreatureBreed_4","Sort":4,"Category":15,"Name":{"Chinese":"帕姆","English":"帕姆"},"Raw":[{"id":"Item_Medicine_30","num":1}],"Product":{"id":"Item_Creature_4","num":1},"TimeCost":120,"ExpRecipe":0},{"ID":"Recipe_CreatureBreed_5","Sort":5,"Category":15,"Name":{"Chinese":"爆豹","English":"爆豹"},"Raw":[{"id":"Item_Medicine_30","num":1}],"Product":{"id":"Item_Creature_5","num":1},"TimeCost":180,"ExpRecipe":0},{"ID":"Recipe_Calculus_8","Sort":8,"Category":16,"Name":{"Chinese":"术法公式总结IV","English":"术法公式总结IV"},"Raw":[{"id":"Item_Magic_4","num":1}],"Product":{"id":"Item_Calculus_8","num":1},"TimeCost":36,"ExpRecipe":60}]